[
    {
        "الدرجة": "90",
        "A": "٢٩+",
        "B": "",
        "C": "٢٣+",
        "D": "١٩+",
        "E": "١٨+",
        "F": "١٢+",
        "G": "١٠+",
        "H": "",
        "I": "",
        "J": "",
        "K": "",
        "L": "",
        "M": "٢٥+",
        "N": "54"
    },
    {
        "الدرجة": "89",
        "A": "28",
        "B": "",
        "C": "22",
        "D": "18",
        "E": "",
        "F": "11",
        "G": "",
        "H": "",
        "I": "",
        "J": "",
        "K": "30",
        "L": "",
        "M": "24",
        "N": "53"
    },
    {
        "الدرجة": "88",
        "A": "",
        "B": "",
        "C": "",
        "D": "",
        "E": "17",
        "F": "",
        "G": "9",
        "H": "",
        "I": "",
        "J": "9",
        "K": "29",
        "L": "",
        "M": "",
        "N": "52"
    },
    {
        "الدرجة": "87",
        "A": "27",
        "B": "",
        "C": "21",
        "D": "17",
        "E": "",
        "F": "",
        "G": "",
        "H": "",
        "I": "",
        "J": "",
        "K": "",
        "L": "",
        "M": "23",
        "N": "51"
    },
    {
        "الدرجة": "86",
        "A": "",
        "B": "",
        "C": "",
        "D": "",
        "E": "",
        "F": "",
        "G": "",
        "H": "",
        "I": "21",
        "J": "",
        "K": "28",
        "L": "",
        "M": "",
        "N": "50"
    },
    {
        "الدرجة": "85",
        "A": "26",
        "B": "",
        "C": "20",
        "D": "",
        "E": "16",
        "F": "10",
        "G": "",
        "H": "",
        "I": "",
        "J": "",
        "K": "",
        "L": "",
        "M": "22",
        "N": "49"
    },
    {
        "الدرجة": "84",
        "A": "",
        "B": "",
        "C": "",
        "D": "16",
        "E": "",
        "F": "",
        "G": "",
        "H": "",
        "I": "20",
        "J": "",
        "K": "27",
        "L": "",
        "M": "",
        "N": "48"
    },
    {
        "الدرجة": "83",
        "A": "25",
        "B": "36",
        "C": "19",
        "D": "",
        "E": "",
        "F": "",
        "G": "8",
        "H": "",
        "I": "",
        "J": "8",
        "K": "26",
        "L": "",
        "M": "21",
        "N": "47"
    },
    {
        "الدرجة": "82",
        "A": "24",
        "B": "35",
        "C": "",
        "D": "",
        "E": "15",
        "F": "",
        "G": "",
        "H": "36",
        "I": "19",
        "J": "",
        "K": "",
        "L": "",
        "M": "",
        "N": "46"
    },
    {
        "الدرجة": "81",
        "A": "",
        "B": "",
        "C": "",
        "D": "15",
        "E": "",
        "F": "9",
        "G": "",
        "H": "",
        "I": "",
        "J": "",
        "K": "25",
        "L": "",
        "M": "20",
        "N": "45"
    },
    {
        "الدرجة": "80",
        "A": "23",
        "B": "34",
        "C": "18",
        "D": "",
        "E": "14",
        "F": "",
        "G": "",
        "H": "35",
        "I": "18",
        "J": "",
        "K": "24",
        "L": "27",
        "M": "",
        "N": "٤٤-٤٣"
    },
    {
        "الدرجة": "79",
        "A": "",
        "B": "33",
        "C": "",
        "D": "14",
        "E": "",
        "F": "",
        "G": "",
        "H": "34",
        "I": "",
        "J": "",
        "K": "",
        "L": "26",
        "M": "19",
        "N": "42"
    },
    {
        "الدرجة": "78",
        "A": "22",
        "B": "32",
        "C": "17",
        "D": "",
        "E": "",
        "F": "",
        "G": "7",
        "H": "33",
        "I": "",
        "J": "7",
        "K": "23",
        "L": "",
        "M": "18",
        "N": "41"
    },
    {
        "الدرجة": "77",
        "A": "",
        "B": "31",
        "C": "",
        "D": "",
        "E": "13",
        "F": "8",
        "G": "",
        "H": "32",
        "I": "17",
        "J": "",
        "K": "",
        "L": "25",
        "M": "",
        "N": "40"
    },
    {
        "الدرجة": "76",
        "A": "21",
        "B": "30",
        "C": "16",
        "D": "13",
        "E": "",
        "F": "",
        "G": "",
        "H": "31",
        "I": "",
        "J": "",
        "K": "22",
        "L": "24",
        "M": "17",
        "N": "39"
    },
    {
        "الدرجة": "75",
        "A": "20",
        "B": "",
        "C": "",
        "D": "",
        "E": "",
        "F": "",
        "G": "",
        "H": "30",
        "I": "16",
        "J": "",
        "K": "21",
        "L": "",
        "M": "",
        "N": "38"
    },
    {
        "الدرجة": "74",
        "A": "",
        "B": "29",
        "C": "15",
        "D": "12",
        "E": "12",
        "F": "",
        "G": "",
        "H": "",
        "I": "",
        "J": "",
        "K": "",
        "L": "23",
        "M": "16",
        "N": "37"
    },
    {
        "الدرجة": "73",
        "A": "19",
        "B": "28",
        "C": "",
        "D": "",
        "E": "",
        "F": "7",
        "G": "6",
        "H": "29",
        "I": "15",
        "J": "",
        "K": "20",
        "L": "22",
        "M": "",
        "N": "36"
    },
    {
        "الدرجة": "72",
        "A": "",
        "B": "27",
        "C": "14",
        "D": "",
        "E": "",
        "F": "",
        "G": "",
        "H": "28",
        "I": "",
        "J": "6",
        "K": "",
        "L": "",
        "M": "15",
        "N": "35"
    },
    {
        "الدرجة": "71",
        "A": "18",
        "B": "26",
        "C": "",
        "D": "11",
        "E": "11",
        "F": "",
        "G": "",
        "H": "27",
        "I": "14",
        "J": "",
        "K": "19",
        "L": "21",
        "M": "",
        "N": "34"
    },
    {
        "الدرجة": "70",
        "A": "",
        "B": "25",
        "C": "13",
        "D": "",
        "E": "",
        "F": "",
        "G": "",
        "H": "26",
        "I": "",
        "J": "",
        "K": "18",
        "L": "20",
        "M": "14",
        "N": "٣٣-٣٢"
    },
    {
        "الدرجة": "69",
        "A": "17",
        "B": "24",
        "C": "",
        "D": "",
        "E": "10",
        "F": "6",
        "G": "",
        "H": "25",
        "I": "13",
        "J": "",
        "K": "",
        "L": "",
        "M": "",
        "N": "31"
    },
    {
        "الدرجة": "68",
        "A": "16",
        "B": "",
        "C": "12",
        "D": "10",
        "E": "",
        "F": "",
        "G": "5",
        "H": "24",
        "I": "",
        "J": "",
        "K": "17",
        "L": "19",
        "M": "13",
        "N": "30"
    },
    {
        "الدرجة": "67",
        "A": "",
        "B": "23",
        "C": "",
        "D": "",
        "E": "",
        "F": "",
        "G": "",
        "H": "23",
        "I": "12",
        "J": "5",
        "K": "16",
        "L": "18",
        "M": "",
        "N": "29"
    },
    {
        "الدرجة": "66",
        "A": "15",
        "B": "22",
        "C": "11",
        "D": "9",
        "E": "9",
        "F": "",
        "G": "",
        "H": "",
        "I": "",
        "J": "",
        "K": "",
        "L": "",
        "M": "12",
        "N": "28"
    },
    {
        "الدرجة": "65",
        "A": "",
        "B": "21",
        "C": "",
        "D": "",
        "E": "",
        "F": "5",
        "G": "",
        "H": "22",
        "I": "11",
        "J": "",
        "K": "15",
        "L": "17",
        "M": "",
        "N": "27"
    },
    {
        "الدرجة": "64",
        "A": "14",
        "B": "20",
        "C": "10",
        "D": "",
        "E": "",
        "F": "",
        "G": "",
        "H": "21",
        "I": "",
        "J": "",
        "K": "",
        "L": "16",
        "M": "11",
        "N": "26"
    },
    {
        "الدرجة": "63",
        "A": "",
        "B": "19",
        "C": "",
        "D": "8",
        "E": "8",
        "F": "",
        "G": "4",
        "H": "20",
        "I": "",
        "J": "",
        "K": "14",
        "L": "",
        "M": "",
        "N": "25"
    },
    {
        "الدرجة": "62",
        "A": "13",
        "B": "",
        "C": "9",
        "D": "",
        "E": "",
        "F": "",
        "G": "",
        "H": "19",
        "I": "10",
        "J": "4",
        "K": "13",
        "L": "15",
        "M": "10",
        "N": "24"
    },
    {
        "الدرجة": "61",
        "A": "",
        "B": "18",
        "C": "",
        "D": "7",
        "E": "",
        "F": "4",
        "G": "",
        "H": "18",
        "I": "",
        "J": "",
        "K": "",
        "L": "14",
        "M": "",
        "N": "23"
    },
    {
        "الدرجة": "60",
        "A": "12",
        "B": "17",
        "C": "8",
        "D": "",
        "E": "7",
        "F": "",
        "G": "",
        "H": "17",
        "I": "9",
        "J": "",
        "K": "12",
        "L": "",
        "M": "9",
        "N": "٢٢-٢١"
    },
    {
        "الدرجة": "59",
        "A": "11",
        "B": "16",
        "C": "",
        "D": "",
        "E": "",
        "F": "",
        "G": "",
        "H": "",
        "I": "",
        "J": "",
        "K": "",
        "L": "13",
        "M": "",
        "N": "20"
    },
    {
        "الدرجة": "58",
        "A": "",
        "B": "15",
        "C": "7",
        "D": "6",
        "E": "6",
        "F": "",
        "G": "3",
        "H": "16",
        "I": "8",
        "J": "",
        "K": "11",
        "L": "12",
        "M": "8",
        "N": "19"
    },
    {
        "الدرجة": "57",
        "A": "10",
        "B": "14",
        "C": "",
        "D": "",
        "E": "",
        "F": "3",
        "G": "",
        "H": "15",
        "I": "",
        "J": "3",
        "K": "10",
        "L": "",
        "M": "",
        "N": "18"
    },
    {
        "الدرجة": "56",
        "A": "",
        "B": "13",
        "C": "6",
        "D": "",
        "E": "",
        "F": "",
        "G": "",
        "H": "14",
        "I": "7",
        "J": "",
        "K": "",
        "L": "11",
        "M": "7",
        "N": "17"
    },
    {
        "الدرجة": "55",
        "A": "9",
        "B": "",
        "C": "",
        "D": "5",
        "E": "5",
        "F": "",
        "G": "",
        "H": "13",
        "I": "",
        "J": "",
        "K": "9",
        "L": "10",
        "M": "",
        "N": "16"
    },
    {
        "الدرجة": "54",
        "A": "",
        "B": "12",
        "C": "5",
        "D": "",
        "E": "",
        "F": "",
        "G": "",
        "H": "12",
        "I": "6",
        "J": "",
        "K": "8",
        "L": "",
        "M": "6",
        "N": "15"
    },
    {
        "الدرجة": "53",
        "A": "8",
        "B": "11",
        "C": "",
        "D": "4",
        "E": "",
        "F": "2",
        "G": "2",
        "H": "11",
        "I": "",
        "J": "",
        "K": "",
        "L": "9",
        "M": "",
        "N": "14"
    },
    {
        "الدرجة": "52",
        "A": "7",
        "B": "10",
        "C": "",
        "D": "",
        "E": "4",
        "F": "",
        "G": "",
        "H": "10",
        "I": "5",
        "J": "2",
        "K": "7",
        "L": "8",
        "M": "5",
        "N": "13"
    },
    {
        "الدرجة": "51",
        "A": "",
        "B": "9",
        "C": "4",
        "D": "",
        "E": "",
        "F": "",
        "G": "",
        "H": "",
        "I": "",
        "J": "",
        "K": "",
        "L": "",
        "M": "",
        "N": "12"
    },
    {
        "الدرجة": "50",
        "A": "6",
        "B": "8",
        "C": "",
        "D": "3",
        "E": "",
        "F": "",
        "G": "",
        "H": "9",
        "I": "4",
        "J": "",
        "K": "6",
        "L": "7",
        "M": "4",
        "N": "١١-١٠"
    },
    {
        "الدرجة": "49",
        "A": "",
        "B": "",
        "C": "3",
        "D": "",
        "E": "3",
        "F": "1",
        "G": "",
        "H": "8",
        "I": "",
        "J": "",
        "K": "5",
        "L": "6",
        "M": "",
        "N": "9"
    },
    {
        "الدرجة": "48",
        "A": "5",
        "B": "7",
        "C": "",
        "D": "",
        "E": "",
        "F": "",
        "G": "1",
        "H": "7",
        "I": "3",
        "J": "",
        "K": "",
        "L": "",
        "M": "3",
        "N": "8"
    },
    {
        "الدرجة": "47",
        "A": "",
        "B": "6",
        "C": "2",
        "D": "2",
        "E": "",
        "F": "",
        "G": "",
        "H": "6",
        "I": "",
        "J": "1",
        "K": "4",
        "L": "5",
        "M": "",
        "N": "7"
    },
    {
        "الدرجة": "46",
        "A": "4",
        "B": "5",
        "C": "",
        "D": "",
        "E": "2",
        "F": "",
        "G": "",
        "H": "5",
        "I": "",
        "J": "",
        "K": "",
        "L": "4",
        "M": "2",
        "N": "6"
    },
    {
        "الدرجة": "45",
        "A": "3",
        "B": "4",
        "C": "1",
        "D": "1",
        "E": "",
        "F": "0",
        "G": "",
        "H": "4",
        "I": "2",
        "J": "",
        "K": "3",
        "L": "",
        "M": "",
        "N": "5"
    },
    {
        "الدرجة": "44",
        "A": "",
        "B": "3",
        "C": "",
        "D": "",
        "E": "1",
        "F": "",
        "G": "",
        "H": "",
        "I": "",
        "J": "",
        "K": "2",
        "L": "3",
        "M": "1",
        "N": "4"
    },
    {
        "الدرجة": "43",
        "A": "2",
        "B": "2",
        "C": "0",
        "D": "",
        "E": "",
        "F": "",
        "G": "",
        "H": "3",
        "I": "1",
        "J": "",
        "K": "",
        "L": "2",
        "M": "0",
        "N": "3"
    },
    {
        "الدرجة": "42",
        "A": "",
        "B": "",
        "C": "",
        "D": "0",
        "E": "",
        "F": "",
        "G": "0",
        "H": "2",
        "I": "",
        "J": "",
        "K": "1",
        "L": "",
        "M": "",
        "N": "2"
    },
    {
        "الدرجة": "41",
        "A": "1",
        "B": "1",
        "C": "",
        "D": "",
        "E": "0",
        "F": "",
        "G": "",
        "H": "1",
        "I": "0",
        "J": "0",
        "K": "0",
        "L": "1",
        "M": "",
        "N": "1"
    },
    {
        "الدرجة": "40",
        "A": "",
        "B": "0",
        "C": "",
        "D": "",
        "E": "",
        "F": "",
        "G": "",
        "H": "0",
        "I": "",
        "J": "",
        "K": "",
        "L": "0",
        "M": "",
        "N": "0"
    },
    {
        "الدرجة": "39",
        "A": "0",
        "B": "",
        "C": "",
        "D": "",
        "E": "",
        "F": "",
        "G": "",
        "H": "",
        "I": "",
        "J": "",
        "K": "",
        "L": "",
        "M": "",
        "N": ""
    },
    {
        "الدرجة": "38",
        "A": "",
        "B": "",
        "C": "",
        "D": "",
        "E": "",
        "F": "",
        "G": "",
        "H": "",
        "I": "",
        "J": "",
        "K": "",
        "L": "",
        "M": "",
        "N": ""
    }
]